README.md
setup.cfg
setup.py
flute/__init__.py
flute/model.py
flute/util.py
flute.egg-info/PKG-INFO
flute.egg-info/SOURCES.txt
flute.egg-info/dependency_links.txt
flute.egg-info/requires.txt
flute.egg-info/top_level.txt