Metadata-Version: 1.2
Name: flute
Version: 0.1.9
Summary: Python + Flask Development Framework
Home-page: https://github.com/marcosstefani/flute
Author: Marcos Rosa
Author-email: marcos.cantor@gmail.com
License: UNKNOWN
Keywords: framework python flask sucuri generate
Platform: UNKNOWN
Classifier: Development Status :: 3 - Alpha
Classifier: Intended Audience :: Developers
Classifier: Topic :: Software Development :: Build Tools
Classifier: License :: OSI Approved :: BSD License
Requires-Python: >=3
